deepvac/__init__.py
deepvac/version.py
deepvac/aug/__init__.py
deepvac/aug/base_aug.py
deepvac/aug/composer.py
deepvac/aug/emboss_helper.py
deepvac/aug/face_aug.py
deepvac/aug/factory.py
deepvac/aug/haishoku_helper.py
deepvac/aug/line_helper.py
deepvac/aug/perspective_helper.py
deepvac/aug/remaper_helper.py
deepvac/aug/seg_audit.py
deepvac/aug/seg_aug.py
deepvac/aug/text_aug.py
deepvac/aug/warp_mls_helper.py
deepvac/aug/yolo_aug.py
deepvac/backbones/__init__.py
deepvac/backbones/activate_layer.py
deepvac/backbones/bottleneck_layer.py
deepvac/backbones/conv_layer.py
deepvac/backbones/fpn_layer.py
deepvac/backbones/mobilenet.py
deepvac/backbones/module_helper.py
deepvac/backbones/op_layer.py
deepvac/backbones/regnet.py
deepvac/backbones/repvgg.py
deepvac/backbones/res_layer.py
deepvac/backbones/resnet.py
deepvac/backbones/se_layer.py
deepvac/backbones/spp_layer.py
deepvac/backbones/ssh_layer.py
deepvac/backbones/weights_init.py
deepvac/cast/__init__.py
deepvac/cast/base.py
deepvac/cast/cast_helper.py
deepvac/cast/coreml.py
deepvac/cast/mnn.py
deepvac/cast/ncnn.py
deepvac/cast/onnx.py
deepvac/cast/script.py
deepvac/cast/tensorrt.py
deepvac/cast/tnn.py
deepvac/cast/trace.py
deepvac/core/__init__.py
deepvac/core/config.py
deepvac/core/deepvac.py
deepvac/core/qat.py
deepvac/core/report.py
deepvac/datasets/__init__.py
deepvac/datasets/base_dataset.py
deepvac/datasets/coco.py
deepvac/datasets/file_line.py
deepvac/datasets/os_walk.py
deepvac/experimental/__init__.py
deepvac/experimental/core/__init__.py
deepvac/experimental/core/distill.py
deepvac/experimental/feature/__init__.py
deepvac/experimental/feature/vector.py
deepvac/loss/__init__.py
deepvac/loss/face_loss.py
deepvac/loss/loss.py
deepvac/utils/__init__.py
deepvac/utils/annotation.py
deepvac/utils/crypto.py
deepvac/utils/ddp.py
deepvac/utils/face_align.py
deepvac/utils/face_utils.py
deepvac/utils/log.py
deepvac/utils/meter.py
deepvac/utils/pallete.py
deepvac/utils/time.py
deepvac/utils/user_config.py
deepvac-0.6.0.1.dist-info/LICENSE
deepvac-0.6.0.1.dist-info/METADATA
deepvac-0.6.0.1.dist-info/WHEEL
deepvac-0.6.0.1.dist-info/top_level.txt
deepvac-0.6.0.1.dist-info/RECORD
